cellwars.py
cellwars-0.0.1.dist-info/LICENSE
cellwars-0.0.1.dist-info/METADATA
cellwars-0.0.1.dist-info/WHEEL
cellwars-0.0.1.dist-info/top_level.txt
cellwars-0.0.1.dist-info/RECORD
